agent_sdk/__init__.py
agent_sdk/cli.py
agent_sdk/config.py
agent_sdk/core/__init__.py
agent_sdk/core/agentforce.py
agent_sdk/core/auth.py
agent_sdk/core/base.py
agent_sdk/core/deploy_tools/deploy_zipfile.py
agent_sdk/core/deploy_tools/generate_metadata.py
agent_sdk/core/templates/bots/SampleBot.bot
agent_sdk/core/templates/classes/AtlasRAG.cls
agent_sdk/core/templates/classes/AtlasRAG.cls-meta.xml
agent_sdk/core/templates/classes/LLMMock.cls
agent_sdk/core/templates/classes/LLMMock.cls-meta.xml
agent_sdk/core/templates/classes/QueryDC.cls
agent_sdk/core/templates/classes/QueryDC.cls-meta.xml
agent_sdk/core/templates/classes/QueryDataCloud.cls
agent_sdk/core/templates/classes/QueryDataCloud.cls-meta.xml
agent_sdk/core/templates/classes/QueryEchoAction.cls
agent_sdk/core/templates/classes/QueryEchoAction.cls-meta.xml
agent_sdk/core/templates/genAiFunctions/AnswerQuestionsWithKnowledge/AnswerQuestionsWithKnowledge.genAiFunction-meta.xml
agent_sdk/core/templates/genAiFunctions/AnswerQuestionsWithKnowledge/input/schema.json
agent_sdk/core/templates/genAiFunctions/AnswerQuestionsWithKnowledge/output/schema.json
agent_sdk/core/templates/genAiFunctions/QueryDataCloud/QueryDataCloud.genAiFunction-meta.xml
agent_sdk/core/templates/genAiFunctions/QueryDataCloud/input/schema.json
agent_sdk/core/templates/genAiFunctions/QueryDataCloud/output/schema.json
agent_sdk/core/templates/genAiFunctions/confirm_serviceability/confirm_serviceability.genAiFunction-meta.xml
agent_sdk/core/templates/genAiFunctions/confirm_serviceability/input/schema.json
agent_sdk/core/templates/genAiFunctions/confirm_serviceability/output/schema.json
agent_sdk/core/templates/genAiFunctions/generate_order/generate_order.genAiFunction-meta.xml
agent_sdk/core/templates/genAiFunctions/generate_order/input/schema.json
agent_sdk/core/templates/genAiFunctions/generate_order/output/schema.json
agent_sdk/core/templates/genAiFunctions/update_order/input/schema.json
agentforce_sdk-0.2.1.dist-info/LICENSE
agentforce_sdk-0.2.1.dist-info/METADATA
agentforce_sdk-0.2.1.dist-info/WHEEL
agentforce_sdk-0.2.1.dist-info/entry_points.txt
agentforce_sdk-0.2.1.dist-info/RECORD
