Metadata-Version: 2.3
Name: agentforce-sdk
Version: 0.2.1
Summary: Python SDK for creating, managing, and deploying AI agents in Salesforce
License: Apache-2.0
Author: Agentforce Team
Author-email: agentforce@salesforce.com
Requires-Python: >=3.11,<4.0
Classifier: Programming Language :: Python :: 3
Classifier: Programming Language :: Python :: 3.11
Classifier: License :: OSI Approved :: Apache Software License
Classifier: Operating System :: OS Independent
Classifier: Development Status :: 4 - Beta
Classifier: Intended Audience :: Developers
Classifier: Topic :: Software Development :: Libraries :: Python Modules
Requires-Dist: aiohttp (>=3.8.0)
Requires-Dist: click (>=8.0.0)
Requires-Dist: jsonschema (>=4.0.0)
Requires-Dist: openai (>=1.75.0)
Requires-Dist: pydantic-ai (>=0.1.3)
Requires-Dist: python-dotenv (>=0.20.0)
Requires-Dist: requests (>=2.25.0)
Requires-Dist: simple-salesforce (>=1.12.0)
Requires-Dist: tqdm (>=4.60.0)
